geofinder/__init__.py
geofinder/exceptions.py
geofinder/geofinder.py
geofinder/mcp_server.py
geofinder/pelias.py
geofinder/transformations.py
geofinder/models/__init__.py
geofinder/models/response.py
geofinder/models/result.py
geofinder/utils/__init__.py
geofinder/utils/cache.py
geofinder_icgc-2.3.0.dist-info/licenses/LICENSE
geofinder_icgc-2.3.0.dist-info/METADATA
geofinder_icgc-2.3.0.dist-info/WHEEL
geofinder_icgc-2.3.0.dist-info/entry_points.txt
geofinder_icgc-2.3.0.dist-info/top_level.txt
geofinder_icgc-2.3.0.dist-info/RECORD
