Metadata-Version: 2.4
Name: geofinder-icgc
Version: 2.3.0
Summary: Geocodificador asíncrono para Cataluña usando el servicio ICGC
Author-email: ICGC <qgis.openicgc@icgc.cat>, Goalnefesh <goalnefesh@protonmail.com>
Maintainer-email: Goalnefesh <goalnefesh@protonmail.com>
License: GPL-2.0-or-later
Project-URL: Homepage, https://github.com/jccamel/geofinder-icgc
Project-URL: Documentation, https://www.icgc.cat/es/Herramientas-y-visores/Herramientas/Geocodificador-ICGC
Project-URL: Repository, https://github.com/jccamel/geofinder-icgc
Project-URL: Original Project, https://github.com/OpenICGC/QgisPlugin
Project-URL: Issues, https://github.com/jccamel/geofinder-icgc/issues
Keywords: geocoding,catalonia,icgc,gis,coordinates,pelias,reverse-geocoding,async,fastapi,mcp
Classifier: Development Status :: 4 - Beta
Classifier: Intended Audience :: Developers
Classifier: Intended Audience :: Science/Research
Classifier: License :: OSI Approved :: GNU General Public License v2 or later (GPLv2+)
Classifier: Operating System :: OS Independent
Classifier: Programming Language :: Python :: 3
Classifier: Programming Language :: Python :: 3.10
Classifier: Programming Language :: Python :: 3.11
Classifier: Programming Language :: Python :: 3.12
Classifier: Framework :: AsyncIO
Classifier: Framework :: FastAPI
Classifier: Topic :: Scientific/Engineering :: GIS
Classifier: Topic :: Software Development :: Libraries :: Python Modules
Requires-Python: >=3.10
License-File: LICENSE
Requires-Dist: pydantic>=2.0
Requires-Dist: httpx>=0.27.0
Provides-Extra: gdal
Requires-Dist: GDAL>=3.0; extra == "gdal"
Provides-Extra: pyproj
Requires-Dist: pyproj>=3.0; extra == "pyproj"
Provides-Extra: all
Requires-Dist: pyproj>=3.0; extra == "all"
Provides-Extra: mcp
Requires-Dist: fastmcp>=2.13.0; extra == "mcp"
Provides-Extra: dev
Requires-Dist: pytest>=7.4; extra == "dev"
Requires-Dist: pytest-cov>=4.1; extra == "dev"
Requires-Dist: pytest-mock>=3.11; extra == "dev"
Requires-Dist: ruff>=0.1.0; extra == "dev"
Requires-Dist: mypy>=1.5; extra == "dev"
Requires-Dist: fastmcp>=2.13.0; extra == "dev"
Requires-Dist: pytest-asyncio>=0.23.0; extra == "dev"
Provides-Extra: docs
Requires-Dist: sphinx>=7.0; extra == "docs"
Requires-Dist: sphinx-rtd-theme>=1.3; extra == "docs"
Dynamic: license-file
